[{
        "nome": "Passeio de Barco",
        "imagem": "../../assets/presentes/passeio-de-barco.png",
        "valor": 200,
        "quantidade": 0
    },
    {
        "nome": "Jantar Romatico",
        "imagem": "public/presentes/passeio-de-barco.png",
        "valor": 500,
        "quantidade": 0
    },
    {
        "nome": "Baldinho de Cerveja",
        "imagem": "public/presentes/passeio-de-barco.png",
        "valor": 500,
        "quantidade": 0
    },
    {
        "nome": "Drinks",
        "imagem": "public/presentes/passeio-de-barco.png",
        "valor": 500,
        "quantidade": 0
    },
    {
        "nome": "Mergulho na Ilha do Peixe",
        "imagem": "public/presentes/passeio-de-barco.png",
        "valor": 500,
        "quantidade": 0
    }
]